odoo/addons/shopfloor_dangerous_goods_mobile/README.rst
odoo/addons/shopfloor_dangerous_goods_mobile/__init__.py
odoo/addons/shopfloor_dangerous_goods_mobile/__manifest__.py
odoo/addons/shopfloor_dangerous_goods_mobile/i18n/shopfloor_dangerous_goods_mobile.pot
odoo/addons/shopfloor_dangerous_goods_mobile/readme/CONTRIBUTORS.rst
odoo/addons/shopfloor_dangerous_goods_mobile/readme/DESCRIPTION.rst
odoo/addons/shopfloor_dangerous_goods_mobile/static/description/icon.png
odoo/addons/shopfloor_dangerous_goods_mobile/static/description/index.html
odoo/addons/shopfloor_dangerous_goods_mobile/static/wms/src/components/picking_select.js
odoo/addons/shopfloor_dangerous_goods_mobile/static/wms/src/css/dangerous_goods.css
odoo/addons/shopfloor_dangerous_goods_mobile/static/wms/src/css/limited_quantity_label.png
odoo/addons/shopfloor_dangerous_goods_mobile/static/wms/src/js/demo/demo.checkout.js
odoo/addons/shopfloor_dangerous_goods_mobile/templates/assets.xml
odoo14_addon_shopfloor_dangerous_goods_mobile-14.0.1.1.1.dist-info/METADATA
odoo14_addon_shopfloor_dangerous_goods_mobile-14.0.1.1.1.dist-info/WHEEL
odoo14_addon_shopfloor_dangerous_goods_mobile-14.0.1.1.1.dist-info/top_level.txt
odoo14_addon_shopfloor_dangerous_goods_mobile-14.0.1.1.1.dist-info/RECORD
